udtools/__init__.py
udtools/argparser.py
udtools/cli.py
udtools/data.py
udtools/incident.py
udtools/level1.py
udtools/level2.py
udtools/level3.py
udtools/level4.py
udtools/level5.py
udtools/level6.py
udtools/state.py
udtools/udeval.py
udtools/utils.py
udtools/validator.py
udtools/data/data.json
udtools/data/deprels.json
udtools/data/docdeps.json
udtools/data/docfeats.json
udtools/data/edeprels.json
udtools/data/feats.json
udtools/data/tospace.json
udtools/data/udeprels.json
udtools/data/upos.json
udtools-0.2.7.dist-info/licenses/LICENSE.txt
udtools-0.2.7.dist-info/METADATA
udtools-0.2.7.dist-info/WHEEL
udtools-0.2.7.dist-info/entry_points.txt
udtools-0.2.7.dist-info/top_level.txt
udtools-0.2.7.dist-info/RECORD
