Metadata-Version: 2.4
Name: udtools
Version: 0.2.7
Summary: Python tools for Universal Dependencies
Author: Filip Ginter, Sampo Pyysalo, Daniel Zeman, Milan Straka, Martin Popel, Gosse Bouma, John Bauer, Arianna Masciolini, Ludovica Pannitto
Maintainer-email: Daniel Zeman <zeman@ufal.mff.cuni.cz>
License-Expression: GPL-2.0-or-later
Project-URL: Homepage, https://universaldependencies.org/
Project-URL: Issues, https://github.com/UniversalDependencies/tools/issues
Classifier: Development Status :: 2 - Pre-Alpha
Classifier: Intended Audience :: Science/Research
Classifier: Programming Language :: Python :: 3
Classifier: Operating System :: OS Independent
Requires-Python: >=3.10
License-File: LICENSE.txt
Requires-Dist: udapi>=0.5.0
Requires-Dist: regex>=2020.09.27
Dynamic: license-file
